KAN_synth/__init__.py
KAN_synth/benchmarks/Benchmarks.py
KAN_synth/benchmarks/CTGAN_Efficacy_Comparison_Class.py
KAN_synth/benchmarks/CTGAN_Efficacy_Comparison_Reg.py
KAN_synth/benchmarks/TVAE_Efficacy_Comparison_Class.py
KAN_synth/benchmarks/TVAE_Efficacy_Comparison_Reg.py
KAN_synth/benchmarks/__init__.py
KAN_synth/data_gen/CTGAN_Data_Generation_test.py
KAN_synth/data_gen/TVAE_Data_Generation_test.py
KAN_synth/data_gen/__init__.py
KAN_synth/models/Disc_KAN_CTGAN_code.py
KAN_synth/models/Gen_KAN_CTGAN_code.py
KAN_synth/models/Hybrid_CTGAN_code.py
KAN_synth/models/Hybrid_TVAE_code.py
KAN_synth/models/KAN_CTGAN_code.py
KAN_synth/models/KAN_TVAE_code.py
KAN_synth/models/KAN_code.py
KAN_synth/models/__init__.py
KAN_synth/utilities/Utilities.py
KAN_synth/utilities/__init__.py
kan_synth-0.1.2.dist-info/licenses/LICENSE
kan_synth-0.1.2.dist-info/METADATA
kan_synth-0.1.2.dist-info/WHEEL
kan_synth-0.1.2.dist-info/top_level.txt
kan_synth-0.1.2.dist-info/RECORD
