Metadata-Version: 2.4
Name: KAN-synth
Version: 0.1.2
Summary: Synthetic data generation using KAN-enhanced CTGAN/TVAE architectures
Author-email: Cristian Del Gobbo <cristiandelgobbo87@gmail.com>
License: MIT
Project-URL: Homepage, https://github.com/cris1618/KAN_synth
Classifier: Programming Language :: Python :: 3
Classifier: License :: OSI Approved :: MIT License
Classifier: Operating System :: OS Independent
Classifier: Development Status :: 3 - Alpha
Classifier: Intended Audience :: Developers
Classifier: Topic :: Scientific/Engineering :: Artificial Intelligence
Requires-Python: >=3.8
License-File: LICENSE
Requires-Dist: numpy
Requires-Dist: pandas
Requires-Dist: torch
Requires-Dist: tqdm
Requires-Dist: ctgan
Requires-Dist: sdgym
Requires-Dist: scikit-learn
Requires-Dist: xgboost
Requires-Dist: matplotlib
Requires-Dist: scipy
Dynamic: license-file
